autorch/__init__.py
autorch/function/__init__.py
autorch/function/sp2wt.py
autorch/transferlearning/__init__.py
autorch/transferlearning/wadda.py
autorch/utils/__init__.py
autorch/utils/part.py
autorch-0.3.6.dist-info/LICENSE
autorch-0.3.6.dist-info/METADATA
autorch-0.3.6.dist-info/WHEEL
autorch-0.3.6.dist-info/top_level.txt
autorch-0.3.6.dist-info/RECORD
