Metadata-Version: 2.1
Name: autorch
Version: 0.3.6
Summary: auto pytorch
Home-page: https://github.com/skywalker0803r/autorch
Author: skywalker0803r
Author-email: skywalker0803r@gmail.com
License: UNKNOWN
Platform: UNKNOWN
Requires-Dist: numpy
Requires-Dist: pandas
Requires-Dist: matplotlib
Requires-Dist: scikit-learn
Requires-Dist: joblib
Requires-Dist: torch
Requires-Dist: torch-dct
Requires-Dist: tensorboard
Requires-Dist: tqdm
